spew/__init__.py
spew/__main__.py
spew/generate.py
spew/names.py
spew-1.0.2.dist-info/LICENSE
spew-1.0.2.dist-info/WHEEL
spew-1.0.2.dist-info/METADATA
spew-1.0.2.dist-info/RECORD
